README
setup.py
giblets/__init__.py
giblets/core.py
giblets/policy.py
giblets/search.py
giblets.egg-info/PKG-INFO
giblets.egg-info/SOURCES.txt
giblets.egg-info/dependency_links.txt
giblets.egg-info/entry_points.txt
giblets.egg-info/namespace_packages.txt
giblets.egg-info/requires.txt
giblets.egg-info/top_level.txt
tests/__init__.py
tests/helpers.py
tests/test_core.py
tests/test_documentation.py
tests/test_policy.py
tests/test_search.py
tests/test_plugin_egg/__init__.py
tests/test_plugin_egg/eggmod1.py
tests/test_plugin_egg/eggmod2.py
tests/test_plugin_path/mod1.py
tests/test_plugin_path/mod2.py