Metadata-Version: 1.0
Name: giblets
Version: 0.2
Summary: A simple plugin system based on the component architecture of Trac.
Home-page: http://github.com/ltucker/giblets
Author: Luke Tucker
Author-email: voxluci@gmail.com
License: BSD
Keywords: plugins components
Platform: UNKNOWN
Classifier: Development Status :: 4 - Beta
Classifier: Intended Audience :: Developers
Classifier: License :: OSI Approved :: BSD License
Classifier: Topic :: Software Development
